common_server/__init__.py
common_server/types.py
common_server/server/__init__.py
common_server/server/server.py
common_server/server/task_manager.py
common_server/server/utils.py
common_server/utils/in_memory_cache.py
common_server/utils/push_notification_auth.py
agent2agent_server-0.0.7.dist-info/METADATA
agent2agent_server-0.0.7.dist-info/WHEEL
agent2agent_server-0.0.7.dist-info/licenses/LICENSE
agent2agent_server-0.0.7.dist-info/RECORD
