Metadata-Version: 2.4
Name: agent2agent-server
Version: 0.0.7
Summary: Agent2Agent server utility and boilerplate code from google.
License-File: LICENSE
Requires-Python: >=3.10
Requires-Dist: httpx-sse>=0.4.0
Requires-Dist: httpx>=0.28.1
Requires-Dist: jwcrypto>=1.5.6
Requires-Dist: pydantic>=2.10.6
Requires-Dist: pyjwt>=2.10.1
Requires-Dist: sse-starlette>=2.2.1
Requires-Dist: starlette>=0.46.1
Requires-Dist: typing-extensions>=4.12.2
Requires-Dist: uvicorn>=0.34.0
